hasse/__init__.py
hasse/poset.py
hasse-0.2.0.dist-info/LICENSE
hasse-0.2.0.dist-info/METADATA
hasse-0.2.0.dist-info/WHEEL
hasse-0.2.0.dist-info/RECORD
