Metadata-Version: 2.1
Name: hasse
Version: 0.2.0
Summary: Python library for representing Partially Ordered sets via Hasse Diagrams.
License: MIT
Author: Marcell Vazquez-Chanlatte
Author-email: mvc@linux.com
Requires-Python: >=3.9,<4.0
Classifier: License :: OSI Approved :: MIT License
Classifier: Programming Language :: Python :: 3
Classifier: Programming Language :: Python :: 3.9
Classifier: Programming Language :: Python :: 3.10
Classifier: Programming Language :: Python :: 3.11
Classifier: Programming Language :: Python :: 3.12
Requires-Dist: attrs (>=21.2.0,<22.0.0)
Requires-Dist: networkx (>=2.6.2,<3.0.0)
